codegen_sdk_pink-0.1.0.dist-info/METADATA
codegen_sdk_pink-0.1.0.dist-info/WHEEL
codegen_sdk_pink/__init__.py
codegen_sdk_pink/__init__.pyi
codegen_sdk_pink/py.typed
codegen_sdk_pink/codegen_sdk_pink.abi3.so
codegen_sdk_pink-0.1.0.dist-info/RECORD
