Metadata-Version: 2.4
Name: codegen-sdk-pink
Version: 0.1.0
Summary: Python bindings for pink
Home-Page: https://codegen.sh
Author: Ellen Esha Agarwal <ellenagarwal897@gmail.com>
Author-email: Ellen Esha Agarwal <ellenagarwal897@gmail.com>
License: Apache-2.0
Requires-Python: >=3.11
Project-URL: Source Code, https://github.com/codegen-sh/pink
